templatio/__init__.py
templatio/templatiofun.py
templatio/test_templatiofun.py
templatio-0.1.1.data/scripts/templatio
templatio-0.1.1.dist-info/DESCRIPTION.rst
templatio-0.1.1.dist-info/METADATA
templatio-0.1.1.dist-info/RECORD
templatio-0.1.1.dist-info/WHEEL
templatio-0.1.1.dist-info/metadata.json
templatio-0.1.1.dist-info/top_level.txt
