Metadata-Version: 2.0
Name: templatio
Version: 0.1.1
Summary: Convert text files based on input and output templates
Home-page: https://github.com/marcobellaccini/templatio
Author: Marco Bellaccini
Author-email: UNKNOWN
License: Apache License 2.0
Keywords: convert text template TextFSM Jinja2
Platform: UNKNOWN
Classifier: License :: OSI Approved :: Apache Software License
Classifier: Operating System :: OS Independent
Classifier: Programming Language :: Python :: 3
Classifier: Topic :: Utilities
Requires-Dist: Jinja2
Requires-Dist: textfsm
